README.rst
setup.py
./LICENSE.txt
./__init__.py
./base.py
./connector.py
./example.py
pupu_sqlalchemy_clickhouse.egg-info/PKG-INFO
pupu_sqlalchemy_clickhouse.egg-info/SOURCES.txt
pupu_sqlalchemy_clickhouse.egg-info/dependency_links.txt
pupu_sqlalchemy_clickhouse.egg-info/entry_points.txt
pupu_sqlalchemy_clickhouse.egg-info/requires.txt
pupu_sqlalchemy_clickhouse.egg-info/top_level.txt